file_compass/__init__.py
file_compass/chunker.py
file_compass/cli.py
file_compass/config.py
file_compass/embedder.py
file_compass/explainer.py
file_compass/gateway.py
file_compass/indexer.py
file_compass/merkle.py
file_compass/quick_index.py
file_compass/scanner.py
file_compass/db/.gitkeep
file_compass-0.1.0.dist-info/METADATA
file_compass-0.1.0.dist-info/WHEEL
file_compass-0.1.0.dist-info/entry_points.txt
file_compass-0.1.0.dist-info/licenses/LICENSE
file_compass-0.1.0.dist-info/RECORD
