Metadata-Version: 2.4
Name: file-compass
Version: 0.1.0
Summary: Semantic file search for AI workstations using HNSW indexing
Project-URL: Homepage, https://github.com/mikeyfrilot/file-compass
Project-URL: Repository, https://github.com/mikeyfrilot/file-compass
Project-URL: Issues, https://github.com/mikeyfrilot/file-compass/issues
Author: Mikey Frilot
License-Expression: MIT
License-File: LICENSE
Keywords: embeddings,file-search,hnsw,mcp,ollama,semantic-search
Classifier: Development Status :: 4 - Beta
Classifier: Intended Audience :: Developers
Classifier: License :: OSI Approved :: MIT License
Classifier: Programming Language :: Python :: 3
Classifier: Programming Language :: Python :: 3.10
Classifier: Programming Language :: Python :: 3.11
Classifier: Programming Language :: Python :: 3.12
Classifier: Topic :: Software Development :: Libraries :: Python Modules
Classifier: Topic :: Text Processing :: Indexing
Requires-Python: >=3.10
Requires-Dist: hnswlib>=0.8.0
Requires-Dist: httpx>=0.25.0
Requires-Dist: mcp>=1.0.0
Requires-Dist: numpy>=1.24.0
Provides-Extra: dev
Requires-Dist: pytest-asyncio>=0.21.0; extra == 'dev'
Requires-Dist: pytest>=7.0.0; extra == 'dev'
Requires-Dist: ruff>=0.1.0; extra == 'dev'
